brags/__init__.py
brags/_golib.py
brags/bin/libbrags.so
brags/config_parser/data_types.py
brags/config_parser/parser.py
brags/factories/baseclasses/baseembedding.py
brags/factories/baseclasses/basellm.py
brags/factories/baseclasses/basevectorstore.py
brags/factories/embedding/embeddingFactory.py
brags/factories/embedding/implementations/ensembleEmbedding.py
brags/factories/embedding/implementations/huggingFaceEmbedding.py
brags/factories/llm/implementations/googleGenAILLM.py
brags/factories/llm/implementations/ollamaLLM.py
brags/factories/llm/llmFactory.py
brags/factories/vectorStore/implementations/chroma_vector_store.py
brags/factories/vectorStore/implementations/faiss_vector_store.py
brags/factories/vectorStore/vector_store_factory.py
brags/main.py
brags/main_test.py
brags/pipeline/assembler.py
brags/rag_config.example.yaml
brags/test_documents.py
brags/utils/logging_setup.py
brags/utils/print_rag_config.py
brags/version.py
brags-0.0.5.dist-info/LICENSE
brags-0.0.5.dist-info/METADATA
brags-0.0.5.dist-info/WHEEL
brags-0.0.5.dist-info/RECORD
