Metadata-Version: 2.1
Name: brags
Version: 0.0.5
Summary: Build-your-own Retrieval-Augmented Generation (RAG) system
License: MIT
Author: Omkar Wagholikar
Author-email: omkargwagholikar@gmail.com
Requires-Python: >=3.8,<4.0
Classifier: License :: OSI Approved :: MIT License
Classifier: Programming Language :: Python :: 3
Classifier: Programming Language :: Python :: 3.8
Classifier: Programming Language :: Python :: 3.9
Classifier: Programming Language :: Python :: 3.10
Classifier: Programming Language :: Python :: 3.11
